{
  "name": "orders-cdc",
  "config": {
    "connector.class": "io.debezium.connector.postgresql.PostgresConnector",
    "database.hostname": "postgres",
    "database.port": "5432",
    "database.user": "user",
    "database.password": "admin123",
    "database.dbname": "orders_db",

    "database.server.name": "orders",
    "plugin.name": "pgoutput",

    "table.include.list":
      "public.customer,
       public.orders",

    "slot.name": "orders_slot",
    "publication.autocreate.mode": "filtered",

    "snapshot.mode": "initial",
    "tombstones.on.delete": "false"
  }
}
